TrimLog/Introduction.md
TrimLog/__init__.py
TrimLog/exceptions.py
TrimLog/logger_constants.py
TrimLog/logger_main.py
TrimLog/object_constants.py
TrimLog/pip_manager.py
TrimLog/test.py
TrimLog/utils.py
TrimLog-0.8.3.dist-info/LICENSE
TrimLog-0.8.3.dist-info/METADATA
TrimLog-0.8.3.dist-info/WHEEL
TrimLog-0.8.3.dist-info/top_level.txt
TrimLog-0.8.3.dist-info/RECORD
