Metadata-Version: 2.1
Name: TrimLog
Version: 0.8.3
Summary: TriMO组织的python项目log和项目管理框架库。
Home-page: https://github.com/TriM-Organization/TrimLog
Author: FedDragon1, Eilles Wan, bgArray
Author-email: TriM-Organization@hotmail.com
Classifier: Intended Audience :: Developers
Classifier: Natural Language :: Chinese (Simplified)
Classifier: License :: OSI Approved :: Apache Software License
Classifier: Operating System :: OS Independent
Classifier: Topic :: Software Development :: Libraries
Classifier: Programming Language :: Python
Classifier: Programming Language :: Python :: 3
Classifier: Programming Language :: Python :: 3.6
Classifier: Programming Language :: Python :: 3.7
Classifier: Programming Language :: Python :: 3.8
Classifier: Programming Language :: Python :: 3.9
Classifier: Programming Language :: Python :: 3.10
License-File: LICENSE
Requires-Dist: rich>=10.9.0
Requires-Dist: setuptools
